{"_ts":[1485924336],"_r":{"breakdown":{"html":{"bytes":[367763],"requests":[27]},"js":{"bytes":[889953],"requests":[28]},"css":{"bytes":[31015],"requests":[2]},"image":{"bytes":[657354],"requests":[79]},"flash":{"bytes":[0],"requests":[0]},"font":{"bytes":[114713],"requests":[5]},"other":{"bytes":[7548],"requests":[12]}},"date":[1485924336],"domElements":[1410.2],"domInteractive":[4811.2],"firstPaint":[4511.2],"fullyLoaded":[12482.8],"id":["170201_9B_4HZQ"],"loadTime":[7318.4],"render":[4956],"SpeedIndex":[6488.2],"TTFB":[3430.4],"videoFrames":[[{"_t":0,"_vc":0},{"_t":2500,"_vc":28},{"_t":2800,"_vc":28},{"_t":3300,"_vc":68},{"_t":6300,"_vc":70},{"_t":6500,"_vc":73},{"_t":6700,"_vc":87},{"_t":6800,"_vc":87},{"_t":6900,"_vc":87},{"_t":9500,"_vc":100},{"_t":9900,"_vc":100}]],"visualComplete":[11347.4]}}